om_py/__init__.py
om_py/functions.py
om_py/musicxml2om.py
om_py/neimog.py
om_py/new_communation.py
om_py/om_functions.py
om_py/python_to_om.py
om_py/score.py
om_py-0.0.21.dist-info/COPYING.rst
om_py-0.0.21.dist-info/LICENSE
om_py-0.0.21.dist-info/METADATA
om_py-0.0.21.dist-info/WHEEL
om_py-0.0.21.dist-info/top_level.txt
om_py-0.0.21.dist-info/RECORD
