Metadata-Version: 2.1
Name: om-py
Version: 0.0.21
Summary: This is a simple package to help musicians to general functions.
Home-page: https://github.com/charlesneimog/OM_py
Author: Charles K. Neimog
Author-email: <charlesneimog@outlook.com>
Keywords: python,CAC,OpenMusic
Classifier: Operating System :: Unix
Classifier: Operating System :: MacOS :: MacOS X
Classifier: Operating System :: Microsoft :: Windows
License-File: LICENSE
License-File: COPYING.rst
Requires-Dist: html-to-json
Requires-Dist: python-osc
